CHANGELOG
LICENSE.txt
MANIFEST.in
README.md
requirements.txt
setup.cfg
setup.py
MirMachine.egg-info/PKG-INFO
MirMachine.egg-info/SOURCES.txt
MirMachine.egg-info/dependency_links.txt
MirMachine.egg-info/not-zip-safe
MirMachine.egg-info/requires.txt
MirMachine.egg-info/top_level.txt
mirmachine/__init__.py
mirmachine/determine_mirmachine_cutoffs.R
mirmachine/find_and_apply_tresholds.R
mirmachine/__pycache__/__init__.cpython-310.pyc
mirmachine/meta/__init__.py
mirmachine/meta/family_seeds.tsv
mirmachine/meta/family_seeds_old.tsv
mirmachine/meta/losses_mirnas.tsv
mirmachine/meta/nodes_mirnas_corrected.tsv
mirmachine/meta/nodes_mirnas_corrected_with_terminal.tsv
mirmachine/meta/tree.newick
mirmachine/meta/__pycache__/__init__.cpython-310.pyc
mirmachine/meta/cms/__init__.py
mirmachine/meta/cms/combined/Bantam.PRE.CM
mirmachine/meta/cms/combined/Iab-4.PRE.CM
mirmachine/meta/cms/combined/Let-7.PRE.CM
mirmachine/meta/cms/combined/Lsy-6.PRE.CM
mirmachine/meta/cms/combined/Mir-1.PRE.CM
mirmachine/meta/cms/combined/Mir-10.PRE.CM
mirmachine/meta/cms/combined/Mir-1000.PRE.CM
mirmachine/meta/cms/combined/Mir-1001.PRE.CM
mirmachine/meta/cms/combined/Mir-1003.PRE.CM
mirmachine/meta/cms/combined/Mir-1006.PRE.CM
mirmachine/meta/cms/combined/Mir-1007.PRE.CM
mirmachine/meta/cms/combined/Mir-101.PRE.CM
mirmachine/meta/cms/combined/Mir-1010.PRE.CM
mirmachine/meta/cms/combined/Mir-10182.PRE.CM
mirmachine/meta/cms/combined/Mir-10293.PRE.CM
mirmachine/meta/cms/combined/Mir-103.PRE.CM
mirmachine/meta/cms/combined/Mir-10355.PRE.CM
mirmachine/meta/cms/combined/Mir-10378.PRE.CM
mirmachine/meta/cms/combined/Mir-10485.PRE.CM
mirmachine/meta/cms/combined/Mir-105.PRE.CM
mirmachine/meta/cms/combined/Mir-10585.PRE.CM
mirmachine/meta/cms/combined/Mir-10651.PRE.CM
mirmachine/meta/cms/combined/Mir-11183.PRE.CM
mirmachine/meta/cms/combined/Mir-11187.PRE.CM
mirmachine/meta/cms/combined/Mir-11217.PRE.CM
mirmachine/meta/cms/combined/Mir-11223.PRE.CM
mirmachine/meta/cms/combined/Mir-11228.PRE.CM
mirmachine/meta/cms/combined/Mir-11230.PRE.CM
mirmachine/meta/cms/combined/Mir-11236.PRE.CM
mirmachine/meta/cms/combined/Mir-11272.PRE.CM
mirmachine/meta/cms/combined/Mir-11275.PRE.CM
