Metadata-Version: 2.1
Name: MirMachine
Version: 0.3.0.2
Summary: MirMachine
Home-page: https://github.com/sinanugur/MirMachine
Author: Sinan U. Umu
Author-email: sinanugur@gmail.com
Keywords: RNA miRNA detection prediction
Classifier: License :: OSI Approved :: MIT License
Classifier: Programming Language :: Python :: 3
Classifier: Topic :: Scientific/Engineering :: Bio-Informatics
Provides-Extra: dev
License-File: LICENSE.txt
